mainer.py
mainer-1.0.dev0.dist-info/LICENSE
mainer-1.0.dev0.dist-info/WHEEL
mainer-1.0.dev0.dist-info/METADATA
mainer-1.0.dev0.dist-info/RECORD
